tacos/__init__.py
tacos/utils.py
tacos/attention/__init__.py
tacos/attention/vanilla_attention.py
tacos/ffn/__init__.py
tacos/ffn/vanilla_ffn.py
tacos/norm/__init__.py
tacos/norm/offset_scale.py
tacos/norm/rms_norm.py
tacos/norm/scale_norm.py
tacos/xformers/__init__.py
tacos/xformers/block.py
tacos/xformers/vanilla_transformer.py
tacos-0.0.2.dist-info/LICENSE
tacos-0.0.2.dist-info/METADATA
tacos-0.0.2.dist-info/WHEEL
tacos-0.0.2.dist-info/top_level.txt
tacos-0.0.2.dist-info/RECORD
